{
  "stage": "iceberg_qec_sweep_dense",
  "saved_at": "2026-07-24T16:37:16.969643+00:00",
  "results": {
    "k": 8,
    "h_field": 0.5,
    "J": 1.0,
    "dt": 0.1,
    "device_name": "H2-Emulator",
    "early_exit": true,
    "syndrome_every": 1,
    "points": [
      {
        "t": 0.8,
        "steps": 8,
        "z": 0.8940986484512731,
        "z_err": 0.009940988978323576,
        "mzz": 0.7970085470085471,
        "mzz_err": 0.017885897255032285,
        "discard_rate": 0.532,
        "n_kept": 234,
        "n_shots": 500
      },
      {
        "t": 1.5,
        "steps": 15,
        "z": 0.8950039721094779,
        "z_err": 0.01771266782727329,
        "mzz": 0.8577981651376146,
        "mzz_err": 0.021222311443184094,
        "discard_rate": 0.782,
        "n_kept": 109,
        "n_shots": 500
      },
      {
        "t": 2.0,
        "steps": 20,
        "z": 0.9390738821293887,
        "z_err": 0.016287664944239562,
        "mzz": 0.9024390243902439,
        "mzz_err": 0.025594431314167086,
        "discard_rate": 0.836,
        "n_kept": 82,
        "n_shots": 500
      },
      {
        "t": 2.5,
        "steps": 25,
        "z": 0.8573214099741123,
        "z_err": 0.032591352321232,
        "mzz": 0.83,
        "mzz_err": 0.03308137659586549,
        "discard_rate": 0.9,
        "n_kept": 50,
        "n_shots": 500
      },
      {
        "t": 3.0,
        "steps": 30,
        "z": 0.9107938595233581,
        "z_err": 0.0514294049702097,
        "mzz": 0.8636363636363636,
        "mzz_err": 0.0660435319448325,
        "discard_rate": 0.945,
        "n_kept": 11,
        "n_shots": 200
      }
    ]
  }
}